easynertag/__init__.py
easynertag/core.py
tests/__init__.py
tests/test_make_tag.py
EasyNERTag-0.2.dist-info/LICENSE
EasyNERTag-0.2.dist-info/METADATA
EasyNERTag-0.2.dist-info/WHEEL
EasyNERTag-0.2.dist-info/top_level.txt
EasyNERTag-0.2.dist-info/RECORD
