Metadata-Version: 2.1
Name: EasyNERTag
Version: 0.2
Summary: Easy tagging for annotate NER corpus
Home-page: https://github.com/wannaphong/easynertag
Author: Wannaphong Phatthiyaphaibun
Author-email: wannaphong@yahoo.com
License: Apache Software License 2.0
Project-URL: Documentation, https://github.com/wannaphong/easynertag
Project-URL: Source, https://github.com/wannaphong/easynertag
Project-URL: Bug Reports, https://github.com/wannaphong/easynertag/issues
Keywords: NLP,natural language processing,text analytics,text processing,localization,computational linguistics
Classifier: Development Status :: 3 - Alpha
Classifier: Programming Language :: Python :: 3
Classifier: Intended Audience :: Developers
Classifier: License :: OSI Approved :: Apache Software License
Classifier: Topic :: Scientific/Engineering :: Artificial Intelligence
Classifier: Topic :: Text Processing
Classifier: Topic :: Text Processing :: General
Classifier: Topic :: Text Processing :: Linguistic
Requires-Python: >=3.6
License-File: LICENSE
